<annotation>
	<folder>collectedimages</folder>
	<filename>Y16.JPG</filename>
	<path>C:\Users\xaris\imagesegmentation\Brain Tumor-Master\Tensorflow\workspace\images\collectedimages\Y16.JPG</path>
	<source>
		<database>Unknown</database>
	</source>
	<size>
		<width>313</width>
		<height>360</height>
		<depth>3</depth>
	</size>
	<segmented>0</segmented>
	<object>
		<name>Tumor</name>
		<pose>Unspecified</pose>
		<truncated>0</truncated>
		<difficult>0</difficult>
		<bndbox>
			<xmin>114</xmin>
			<ymin>74</ymin>
			<xmax>275</xmax>
			<ymax>257</ymax>
		</bndbox>
	</object>
</annotation>
